pypowerline/__init__.py
pypowerline/colors.py
pypowerline/configs.py
pypowerline/create_color.py
pypowerline/main.py
pypowerline/segments.py
pypowerline/static.py
pypowerline/symbols.py
pypowerline/utils.py
pypowerline-0.0.32.dist-info/LICENSE
pypowerline-0.0.32.dist-info/METADATA
pypowerline-0.0.32.dist-info/WHEEL
pypowerline-0.0.32.dist-info/entry_points.txt
pypowerline-0.0.32.dist-info/top_level.txt
pypowerline-0.0.32.dist-info/RECORD
